LICENSE
MANIFEST.in
README.rst
setup.py
docs/Makefile
docs/requirements.txt
docs/source/changelog.rst
docs/source/conf.py
docs/source/index.rst
docs/source/_static/propylon/PropylonFooterFrontpage.jpg
docs/source/_static/propylon/PropylonHeadFrontpage.jpg
docs/source/_static/propylon/PropylonHeadPropylon.jpg
docs/source/_static/propylon/PropylonSpace.png
docs/source/_static/propylon/PropylonSpace.svg
docs/source/_static/propylon/propylon.sty
docs/source/topics/introduction.rst
docs/source/topics/settings.rst
src/django_version_endpoint.egg-info/PKG-INFO
src/django_version_endpoint.egg-info/SOURCES.txt
src/django_version_endpoint.egg-info/dependency_links.txt
src/django_version_endpoint.egg-info/requires.txt
src/django_version_endpoint.egg-info/top_level.txt
src/version_endpoint/__init__.py
src/version_endpoint/apps.py
src/version_endpoint/settings.py
src/version_endpoint/urls.py
src/version_endpoint/utils.py
src/version_endpoint/versions.py
src/version_endpoint/views.py
src/version_endpoint/templates/version_endpoint.html
src/version_endpoint/templates/version_endpoint_single.html